morse_lang/__init__.py
morse_lang/cli.py
morse_lang/interpreter.py
morse_lang/lexer.py
morse_lang/morse_map.py
morse_lang/parser.py
morse_lang-1.1.0.dist-info/METADATA
morse_lang-1.1.0.dist-info/WHEEL
morse_lang-1.1.0.dist-info/entry_points.txt
morse_lang-1.1.0.dist-info/top_level.txt
morse_lang-1.1.0.dist-info/RECORD
