Metadata-Version: 2.4
Name: morse-lang
Version: 1.1.0
Summary: Morse programming language
Home-page: https://github.com/sharky-3/morse-programming-language
Author: Blaz
Author-email: Blaz <you@example.com>
License: MIT
Classifier: Programming Language :: Python :: 3
Classifier: License :: OSI Approved :: MIT License
Classifier: Operating System :: OS Independent
Requires-Python: >=3.9
